commands/API.txt
commands/CodingGoals.py
commands/__init__.py
commands/allTimeSinceToday.py
commands/languageData.py
commands/main.py
commands/projects.py
CodingMetrics-1.0.1.dist-info/LICENSE
CodingMetrics-1.0.1.dist-info/METADATA
CodingMetrics-1.0.1.dist-info/WHEEL
CodingMetrics-1.0.1.dist-info/entry_points.txt
CodingMetrics-1.0.1.dist-info/top_level.txt
CodingMetrics-1.0.1.dist-info/RECORD
