Metadata-Version: 2.1
Name: CodingMetrics
Version: 1.0.1
Summary: Your coding activity tracker
Home-page: https://github.com/premalrupnur/CodingCLI
Author: Premal Rupnur
Author-email: premalrupnur2001@gmail.com
License: MIT
Platform: UNKNOWN
Classifier: Programming Language :: Python :: 3
Classifier: License :: OSI Approved :: MIT License
Classifier: Operating System :: OS Independent
Requires-Dist: certifi (==2020.12.5)
Requires-Dist: chardet (==4.0.0)
Requires-Dist: colorama (==0.4.4)
Requires-Dist: halo (==0.0.31)
Requires-Dist: idna (==2.10)
Requires-Dist: log-symbols (==0.0.14)
Requires-Dist: requests (==2.25.1)
Requires-Dist: six (==1.15.0)
Requires-Dist: spinners (==0.0.24)
Requires-Dist: tabulate (==0.8.7)
Requires-Dist: termcolor (==1.1.0)
Requires-Dist: urllib3 (==1.26.3)
